LICENSE.md
MANIFEST.in
README.md
pyproject.toml
setup.py
./LICENSE.md
src/underworld/__init__.py
src/underworld/_stgermain.py
src/underworld/_uwid.py
src/underworld/_version.py
src/underworld/mpi.py
src/underworld/timing.py
src/underworld.egg-info/PKG-INFO
src/underworld.egg-info/SOURCES.txt
src/underworld.egg-info/dependency_links.txt
src/underworld.egg-info/not-zip-safe
src/underworld.egg-info/requires.txt
src/underworld.egg-info/top_level.txt
src/underworld/UWGeodynamics/__init__.py
src/underworld/UWGeodynamics/_boundary_conditions.py
src/underworld/UWGeodynamics/_density.py
src/underworld/UWGeodynamics/_freesurface.py
src/underworld/UWGeodynamics/_frictional_boundary.py
src/underworld/UWGeodynamics/_material.py
src/underworld/UWGeodynamics/_melt.py
src/underworld/UWGeodynamics/_mesh_advector.py
src/underworld/UWGeodynamics/_model.py
src/underworld/UWGeodynamics/_rcParams.py
src/underworld/UWGeodynamics/_remeshing.py
src/underworld/UWGeodynamics/_rheology.py
src/underworld/UWGeodynamics/_utils.py
src/underworld/UWGeodynamics/_validate.py
src/underworld/UWGeodynamics/_visugrid.py
src/underworld/UWGeodynamics/shapes.py
src/underworld/UWGeodynamics/surfaceProcesses.py
src/underworld/UWGeodynamics/LecodeIsostasy/LecodeIsostasy.py
src/underworld/UWGeodynamics/LecodeIsostasy/__init__.py
src/underworld/UWGeodynamics/lithopress/__init__.py
src/underworld/UWGeodynamics/lithopress/lithopress.py
src/underworld/UWGeodynamics/postprocessing/__init__.py
src/underworld/UWGeodynamics/postprocessing/_logFile.py
src/underworld/UWGeodynamics/postprocessing/_tracers.py
src/underworld/UWGeodynamics/resources/Liquidus.json
src/underworld/UWGeodynamics/resources/Materials.json
src/underworld/UWGeodynamics/resources/PlasticRheologies.json
src/underworld/UWGeodynamics/resources/Solidus.json
src/underworld/UWGeodynamics/resources/ViscousRheologies.json
src/underworld/UWGeodynamics/utilities/UWtoAscii.py
src/underworld/UWGeodynamics/utilities/__init__.py
src/underworld/UWGeodynamics/uwgeo-data/uwgeodynamicsrc
src/underworld/_net/__init__.py
src/underworld/conditions/__init__.py
src/underworld/conditions/_conditions.py
src/underworld/container/__init__.py
src/underworld/container/_indexset.py
