Metadata-Version: 2.2
Name: underworld
Version: 2.16.4
Summary: Underworld2 is a python-friendly, parallel, scalable, easy-to-use toolkit for solving problems in solid and fluid mechanics.
Home-page: https://github.com/underworldcode/underworld2
Download-URL: 
Author-email: Louis Moresi <louis.moresi@anu.edu.au>, Julian Giordani <julian.giordnai@sydney.edu.au>, John Mansour <john.mansour@gmail.com>, Romain Beaucher <romain.beucher@anu.edu.au>
Maintainer-email: Underworld Team <help@underworldcode.org>
License: ### Summary
Project-URL: homepage, https://www.underworldcode.org
Project-URL: repository, https://github.com/underworldcode/underworld2
Project-URL: documentation, https://underworld2.readthedocs.io/en/latest/
Keywords: Underworld,MPI,Geodynamics
Platform: POSIX
Classifier: Development Status :: 5 - Production/Stable
Classifier: Intended Audience :: Developers
Classifier: Intended Audience :: Science/Research
Classifier: Operating System :: POSIX
Classifier: Programming Language :: C
Classifier: Programming Language :: C++
Classifier: Programming Language :: Python
Classifier: Topic :: Scientific/Engineering
Classifier: Topic :: Software Development :: Libraries
Provides: underworld
Requires-Python: >=3.8
License-File: LICENSE.md
Requires-Dist: numpy<2.0
Requires-Dist: mpi4py
Requires-Dist: h5py
Requires-Dist: pint
Requires-Dist: scipy
Provides-Extra: full
Requires-Dist: badlands; extra == "full"
Requires-Dist: lavavu; extra == "full"
Requires-Dist: matplotlib; extra == "full"
Requires-Dist: nbmake; extra == "full"
Dynamic: home-page
Dynamic: platform
Dynamic: provides
